vector_db_at_home/__init__.py
vector_db_at_home/schema.sql
vector_db_at_home/vector_store.py
vector_db_at_home-0.0.2.dist-info/WHEEL
vector_db_at_home-0.0.2.dist-info/METADATA
vector_db_at_home-0.0.2.dist-info/RECORD
