Metadata-Version: 2.3
Name: vector-db-at-home
Version: 0.0.2
Summary: vector db at home
Requires-Dist: numpy>=2.3.2
Requires-Python: >=3.12
